odoo/addons/base_tier_validation_formula/README.rst
odoo/addons/base_tier_validation_formula/__init__.py
odoo/addons/base_tier_validation_formula/__manifest__.py
odoo/addons/base_tier_validation_formula/i18n/base_tier_validation_formula.pot
odoo/addons/base_tier_validation_formula/i18n/es.po
odoo/addons/base_tier_validation_formula/i18n/it.po
odoo/addons/base_tier_validation_formula/i18n/tr.po
odoo/addons/base_tier_validation_formula/i18n/zh_CN.po
odoo/addons/base_tier_validation_formula/models/__init__.py
odoo/addons/base_tier_validation_formula/models/tier_definition.py
odoo/addons/base_tier_validation_formula/models/tier_review.py
odoo/addons/base_tier_validation_formula/models/tier_validation.py
odoo/addons/base_tier_validation_formula/readme/CONTRIBUTORS.md
odoo/addons/base_tier_validation_formula/readme/CREDITS.md
odoo/addons/base_tier_validation_formula/readme/DESCRIPTION.md
odoo/addons/base_tier_validation_formula/readme/USAGE.md
odoo/addons/base_tier_validation_formula/static/description/icon.png
odoo/addons/base_tier_validation_formula/static/description/index.html
odoo/addons/base_tier_validation_formula/tests/__init__.py
odoo/addons/base_tier_validation_formula/tests/test_tier_validation.py
odoo/addons/base_tier_validation_formula/views/tier_definition_view.xml
odoo_addon_base_tier_validation_formula-18.0.1.0.0.4.dist-info/METADATA
odoo_addon_base_tier_validation_formula-18.0.1.0.0.4.dist-info/WHEEL
odoo_addon_base_tier_validation_formula-18.0.1.0.0.4.dist-info/top_level.txt
odoo_addon_base_tier_validation_formula-18.0.1.0.0.4.dist-info/RECORD
