Metadata-Version: 2.1
Name: odoo-addon-base_tier_validation_formula
Version: 18.0.1.0.0.4
Requires-Python: >=3.10
Requires-Dist: odoo-addon-base_tier_validation==18.0.*
Requires-Dist: odoo==18.0.*
Summary: Formulas for Base tier validation
Home-page: https://github.com/OCA/server-ux
License: AGPL-3
Author: Creu Blanca,Odoo Community Association (OCA)
Author-email: support@odoo-community.org
Classifier: Programming Language :: Python
Classifier: Framework :: Odoo
Classifier: Framework :: Odoo :: 18.0
Classifier: License :: OSI Approved :: GNU Affero General Public License v3
Classifier: Development Status :: 6 - Mature
